{
    "constellation_id": 20000080,
    "name": "GPLB-C",
    "planets": [
        {
            "planet_id": 40034484
        },
        {
            "planet_id": 40034485
        },
        {
            "moons": [
                40034488
            ],
            "planet_id": 40034487
        },
        {
            "planet_id": 40034489
        },
        {
            "moons": [
                40034491
            ],
            "planet_id": 40034490
        },
        {
            "moons": [
                40034493
            ],
            "planet_id": 40034492
        },
        {
            "moons": [
                40034495,
                40034496
            ],
            "planet_id": 40034494
        },
        {
            "moons": [
                40034498,
                40034499,
                40034500,
                40034501,
                40034502,
                40034503,
                40034504,
                40034505,
                40034506
            ],
            "planet_id": 40034497
        },
        {
            "moons": [
                40034511
            ],
            "planet_id": 40034508
        },
        {
            "moons": [
                40034516,
                40034517,
                40034518,
                40034519,
                40034520,
                40034522,
                40034523,
                40034524,
                40034525,
                40034526,
                40034527,
                40034530,
                40034532,
                40034534,
                40034535
            ],
            "planet_id": 40034513
        },
        {
            "planet_id": 40034537
        },
        {
            "planet_id": 40034539
        },
        {
            "moons": [
                40034542,
                40034543,
                40034544,
                40034545,
                40034546,
                40034547,
                40034548
            ],
            "planet_id": 40034541
        },
        {
            "moons": [
                40034553,
                40034554
            ],
            "planet_id": 40034550
        }
    ],
    "position": {
        "x": 111875499184773810,
        "y": -4427459566391882,
        "z": -144551103740458600
    },
    "security_class": "I1",
    "security_status": -0.25469717383384705,
    "star_id": 40034483,
    "stargates": [
        50000074,
        50000075,
        50000076,
        50000077
    ],
    "system_id": 30000552
}