{
    "constellation_id": 20000764,
    "name": "Serren",
    "planets": [
        {
            "planet_id": 40330059
        },
        {
            "asteroid_belts": [
                40330061
            ],
            "planet_id": 40330060
        },
        {
            "moons": [
                40330063
            ],
            "planet_id": 40330062
        },
        {
            "asteroid_belts": [
                40330065
            ],
            "moons": [
                40330066
            ],
            "planet_id": 40330064
        },
        {
            "moons": [
                40330068
            ],
            "planet_id": 40330067
        },
        {
            "moons": [
                40330070,
                40330071,
                40330072,
                40330073,
                40330074,
                40330075,
                40330076,
                40330077,
                40330078
            ],
            "planet_id": 40330069
        },
        {
            "asteroid_belts": [
                40330080,
                40330081,
                40330088,
                40330089
            ],
            "moons": [
                40330082,
                40330083,
                40330084,
                40330085,
                40330086,
                40330087
            ],
            "planet_id": 40330079
        },
        {
            "asteroid_belts": [
                40330091,
                40330092,
                40330097,
                40330103,
                40330107
            ],
            "moons": [
                40330093,
                40330094,
                40330095,
                40330096,
                40330098,
                40330099,
                40330100,
                40330101,
                40330102,
                40330104,
                40330105,
                40330106,
                40330108,
                40330109,
                40330110,
                40330111,
                40330112,
                40330113,
                40330114,
                40330115,
                40330116,
                40330117,
                40330118,
                40330119
            ],
            "planet_id": 40330090
        },
        {
            "moons": [
                40330121,
                40330122,
                40330123
            ],
            "planet_id": 40330120
        }
    ],
    "position": {
        "x": -237392383169479420,
        "y": 33373605528786428,
        "z": 51710311557516
    },
    "security_class": "B1",
    "security_status": 0.4588785171508789,
    "star_id": 40330058,
    "stargates": [
        50005514,
        50005515,
        50005516
    ],
    "stations": [
        60007885
    ],
    "system_id": 30005222
}