{
    "constellation_id": 20000163,
    "name": "B2J-5N",
    "planets": [
        {
            "planet_id": 40070924
        },
        {
            "moons": [
                40070926
            ],
            "planet_id": 40070925
        },
        {
            "planet_id": 40070927
        },
        {
            "asteroid_belts": [
                40070929
            ],
            "moons": [
                40070930,
                40070931
            ],
            "planet_id": 40070928
        },
        {
            "moons": [
                40070933,
                40070934
            ],
            "planet_id": 40070932
        },
        {
            "asteroid_belts": [
                40070936
            ],
            "moons": [
                40070937,
                40070938,
                40070939
            ],
            "planet_id": 40070935
        },
        {
            "asteroid_belts": [
                40070941
            ],
            "moons": [
                40070942
            ],
            "planet_id": 40070940
        },
        {
            "moons": [
                40070944,
                40070945,
                40070946,
                40070947,
                40070948,
                40070949,
                40070950,
                40070951,
                40070952,
                40070953,
                40070954,
                40070955,
                40070956,
                40070957,
                40070958,
                40070959
            ],
            "planet_id": 40070943
        },
        {
            "asteroid_belts": [
                40070962,
                40070972,
                40070981,
                40070982,
                40070983,
                40070985,
                40070986,
                40070989
            ],
            "moons": [
                40070961,
                40070963,
                40070964,
                40070965,
                40070966,
                40070967,
                40070968,
                40070969,
                40070970,
                40070971,
                40070973,
                40070974,
                40070975,
                40070976,
                40070977,
                40070978,
                40070979,
                40070980,
                40070984,
                40070987,
                40070988
            ],
            "planet_id": 40070960
        },
        {
            "asteroid_belts": [
                40070991,
                40070992
            ],
            "planet_id": 40070990
        },
        {
            "moons": [
                40070994,
                40070995,
                40070996,
                40070997,
                40070998
            ],
            "planet_id": 40070993
        }
    ],
    "position": {
        "x": 189799837436171170,
        "y": 51043053185525550,
        "z": 59002060000307720
    },
    "security_class": "K5",
    "security_status": -0.5938111543655396,
    "star_id": 40070923,
    "stargates": [
        50010044,
        50010045
    ],
    "system_id": 30001115
}