{
    "constellation_id": 20000076,
    "name": "0IF-26",
    "planets": [
        {
            "planet_id": 40032581
        },
        {
            "planet_id": 40032582
        },
        {
            "planet_id": 40032584
        },
        {
            "moons": [
                40032587
            ],
            "planet_id": 40032585
        },
        {
            "moons": [
                40032589
            ],
            "planet_id": 40032588
        },
        {
            "moons": [
                40032592
            ],
            "planet_id": 40032590
        },
        {
            "moons": [
                40032594,
                40032595,
                40032596,
                40032597,
                40032598,
                40032599,
                40032600
            ],
            "planet_id": 40032593
        },
        {
            "moons": [
                40032602,
                40032603,
                40032604,
                40032605,
                40032606,
                40032607,
                40032608,
                40032609,
                40032610,
                40032611,
                40032612,
                40032613,
                40032615,
                40032616,
                40032617
            ],
            "planet_id": 40032601
        },
        {
            "moons": [
                40032619,
                40032620,
                40032621
            ],
            "planet_id": 40032618
        },
        {
            "moons": [
                40032623,
                40032624,
                40032625,
                40032626
            ],
            "planet_id": 40032622
        },
        {
            "moons": [
                40032628,
                40032629,
                40032630,
                40032631
            ],
            "planet_id": 40032627
        }
    ],
    "position": {
        "x": 137149898705822350,
        "y": -27368270662480980,
        "z": -210393366450242020
    },
    "security_class": "F2",
    "security_status": -0.3963358998298645,
    "star_id": 40032580,
    "stargates": [
        50006687
    ],
    "system_id": 30000522
}