{
    "constellation_id": 20000149,
    "name": "8G-MQV",
    "planets": [
        {
            "moons": [
                40064753
            ],
            "planet_id": 40064752
        },
        {
            "moons": [
                40064755
            ],
            "planet_id": 40064754
        },
        {
            "moons": [
                40064757,
                40064758
            ],
            "planet_id": 40064756
        },
        {
            "moons": [
                40064760,
                40064763,
                40064764,
                40064765,
                40064767,
                40064768,
                40064769,
                40064770,
                40064771,
                40064772,
                40064773,
                40064774,
                40064776
            ],
            "planet_id": 40064759
        },
        {
            "moons": [
                40064778,
                40064780,
                40064781,
                40064782,
                40064783,
                40064784,
                40064785,
                40064786,
                40064787,
                40064788,
                40064789,
                40064790,
                40064791,
                40064792,
                40064793,
                40064794,
                40064795,
                40064796,
                40064797,
                40064798,
                40064799
            ],
            "planet_id": 40064777
        },
        {
            "moons": [
                40064803,
                40064804,
                40064805,
                40064806,
                40064807,
                40064808,
                40064809,
                40064810,
                40064811,
                40064812,
                40064813,
                40064814,
                40064815,
                40064817,
                40064819,
                40064820,
                40064821
            ],
            "planet_id": 40064802
        }
    ],
    "position": {
        "x": 20932220852111244,
        "y": 19201127138454332,
        "z": -145712511564700130
    },
    "security_class": "I",
    "security_status": -0.02503834292292595,
    "star_id": 40064751,
    "stargates": [
        50000096,
        50000097
    ],
    "system_id": 30001017
}