{
    "constellation_id": 20000332,
    "name": "Azizora",
    "planets": [
        {
            "asteroid_belts": [
                40144253
            ],
            "planet_id": 40144252
        },
        {
            "moons": [
                40144255
            ],
            "planet_id": 40144254
        },
        {
            "asteroid_belts": [
                40144257
            ],
            "moons": [
                40144258
            ],
            "planet_id": 40144256
        },
        {
            "asteroid_belts": [
                40144263,
                40144278
            ],
            "moons": [
                40144260,
                40144261,
                40144262,
                40144264,
                40144265,
                40144266,
                40144267,
                40144268,
                40144269,
                40144270,
                40144271,
                40144272,
                40144273,
                40144274,
                40144275,
                40144276,
                40144277
            ],
            "planet_id": 40144259
        },
        {
            "asteroid_belts": [
                40144280,
                40144282,
                40144284,
                40144298,
                40144300,
                40144301
            ],
            "moons": [
                40144281,
                40144283,
                40144285,
                40144286,
                40144287,
                40144288,
                40144289,
                40144290,
                40144291,
                40144292,
                40144293,
                40144294,
                40144295,
                40144296,
                40144297,
                40144299,
                40144302
            ],
            "planet_id": 40144279
        },
        {
            "moons": [
                40144304,
                40144305,
                40144306,
                40144307,
                40144308,
                40144309
            ],
            "planet_id": 40144303
        },
        {
            "asteroid_belts": [
                40144311,
                40144313
            ],
            "moons": [
                40144312,
                40144314
            ],
            "planet_id": 40144310
        }
    ],
    "position": {
        "x": -183483852908187500,
        "y": 55519302988139270,
        "z": -98396170606204240
    },
    "security_class": "B1",
    "security_status": 0.6230301856994629,
    "star_id": 40144251,
    "stargates": [
        50010816,
        50010817,
        50010818
    ],
    "stations": [
        60007756,
        60009007
    ],
    "system_id": 30002265
}