{
    "constellation_id": 20000620,
    "name": "Yehaba",
    "planets": [
        {
            "planet_id": 40268310
        },
        {
            "planet_id": 40268311
        },
        {
            "asteroid_belts": [
                40268313,
                40268314
            ],
            "planet_id": 40268312
        },
        {
            "moons": [
                40268316
            ],
            "planet_id": 40268315
        },
        {
            "asteroid_belts": [
                40268318
            ],
            "moons": [
                40268319
            ],
            "planet_id": 40268317
        },
        {
            "moons": [
                40268321
            ],
            "planet_id": 40268320
        },
        {
            "moons": [
                40268323,
                40268324
            ],
            "planet_id": 40268322
        },
        {
            "moons": [
                40268326
            ],
            "planet_id": 40268325
        },
        {
            "asteroid_belts": [
                40268328
            ],
            "moons": [
                40268329
            ],
            "planet_id": 40268327
        },
        {
            "moons": [
                40268331,
                40268332,
                40268333,
                40268334,
                40268335
            ],
            "planet_id": 40268330
        },
        {
            "moons": [
                40268337,
                40268338,
                40268339
            ],
            "planet_id": 40268336
        },
        {
            "asteroid_belts": [
                40268341,
                40268342,
                40268344
            ],
            "moons": [
                40268343,
                40268345,
                40268346,
                40268347
            ],
            "planet_id": 40268340
        }
    ],
    "position": {
        "x": -331143599304815040,
        "y": 21499083220304920,
        "z": -40063203135806660
    },
    "security_class": "B3",
    "security_status": 0.24170655012130737,
    "star_id": 40268309,
    "stargates": [
        50010608,
        50010609,
        50010610
    ],
    "stations": [
        60006121
    ],
    "system_id": 30004236
}