{
    "constellation_id": 20000111,
    "name": "5-2PQU",
    "planets": [
        {
            "planet_id": 40047973
        },
        {
            "planet_id": 40047975
        },
        {
            "moons": [
                40047977
            ],
            "planet_id": 40047976
        },
        {
            "moons": [
                40047979,
                40047980,
                40047981
            ],
            "planet_id": 40047978
        },
        {
            "moons": [
                40047983
            ],
            "planet_id": 40047982
        },
        {
            "moons": [
                40047985,
                40047986,
                40047987,
                40047988
            ],
            "planet_id": 40047984
        },
        {
            "moons": [
                40047990,
                40047991,
                40047992,
                40047993,
                40047994,
                40047995,
                40047996,
                40047999,
                40048000,
                40048001,
                40048002,
                40048003,
                40048004,
                40048005,
                40048006,
                40048007,
                40048008,
                40048009,
                40048010
            ],
            "planet_id": 40047989
        },
        {
            "moons": [
                40048013,
                40048014,
                40048015,
                40048016,
                40048017,
                40048018,
                40048019,
                40048020,
                40048021,
                40048022,
                40048023,
                40048024,
                40048025,
                40048026,
                40048027,
                40048028
            ],
            "planet_id": 40048012
        },
        {
            "moons": [
                40048032,
                40048033
            ],
            "planet_id": 40048030
        },
        {
            "moons": [
                40048038,
                40048039,
                40048040,
                40048043,
                40048044,
                40048045,
                40048046,
                40048047,
                40048048,
                40048049,
                40048050,
                40048052,
                40048054,
                40048055,
                40048057,
                40048059,
                40048063
            ],
            "planet_id": 40048034
        },
        {
            "moons": [
                40048065,
                40048066,
                40048068,
                40048069,
                40048070,
                40048071,
                40048072,
                40048073,
                40048074,
                40048075,
                40048076,
                40048077,
                40048078,
                40048079,
                40048080,
                40048081,
                40048082,
                40048083,
                40048084,
                40048086,
                40048088,
                40048091
            ],
            "planet_id": 40048064
        }
    ],
    "position": {
        "x": 159060064628867070,
        "y": 8318302803622627,
        "z": -131553073605393680
    },
    "security_class": "F",
    "security_status": -0.08096009492874146,
    "star_id": 40047972,
    "stargates": [
        50001735,
        50001736,
        50001737,
        50001738
    ],
    "system_id": 30000762
}