{
    "constellation_id": 20000461,
    "name": "Z-MO29",
    "planets": [
        {
            "asteroid_belts": [
                40200332
            ],
            "planet_id": 40200331
        },
        {
            "planet_id": 40200333
        },
        {
            "moons": [
                40200335
            ],
            "planet_id": 40200334
        },
        {
            "moons": [
                40200337
            ],
            "planet_id": 40200336
        },
        {
            "asteroid_belts": [
                40200339
            ],
            "moons": [
                40200340
            ],
            "planet_id": 40200338
        },
        {
            "moons": [
                40200342,
                40200343,
                40200344
            ],
            "planet_id": 40200341
        },
        {
            "moons": [
                40200346,
                40200347
            ],
            "planet_id": 40200345
        },
        {
            "asteroid_belts": [
                40200375
            ],
            "moons": [
                40200349,
                40200350,
                40200351,
                40200352,
                40200353,
                40200354,
                40200355,
                40200356,
                40200357,
                40200358,
                40200359,
                40200360,
                40200361,
                40200362,
                40200363,
                40200364,
                40200365,
                40200366,
                40200367,
                40200368,
                40200369,
                40200370,
                40200371,
                40200372,
                40200373,
                40200374,
                40200376
            ],
            "planet_id": 40200348
        },
        {
            "moons": [
                40200378,
                40200379
            ],
            "planet_id": 40200377
        },
        {
            "asteroid_belts": [
                40200381,
                40200383
            ],
            "moons": [
                40200382
            ],
            "planet_id": 40200380
        }
    ],
    "position": {
        "x": -83011592615517090,
        "y": 7718143298276076,
        "z": -446821048679831700
    },
    "security_class": "G",
    "security_status": -0.03704017400741577,
    "star_id": 40200330,
    "stargates": [
        50010147,
        50010148,
        50010149
    ],
    "system_id": 30003154
}