{
    "constellation_id": 20000682,
    "name": "O-MCZR",
    "planets": [
        {
            "moons": [
                40295214
            ],
            "planet_id": 40295213
        },
        {
            "moons": [
                40295216
            ],
            "planet_id": 40295215
        },
        {
            "moons": [
                40295218
            ],
            "planet_id": 40295217
        },
        {
            "asteroid_belts": [
                40295220
            ],
            "moons": [
                40295221,
                40295222,
                40295223,
                40295224,
                40295225,
                40295226,
                40295227,
                40295228,
                40295229,
                40295230,
                40295231,
                40295232,
                40295233,
                40295234,
                40295235,
                40295236,
                40295237,
                40295238,
                40295239,
                40295240
            ],
            "planet_id": 40295219
        },
        {
            "asteroid_belts": [
                40295243,
                40295245,
                40295246,
                40295259,
                40295261,
                40295263,
                40295265,
                40295268,
                40295270
            ],
            "moons": [
                40295242,
                40295244,
                40295247,
                40295248,
                40295249,
                40295250,
                40295251,
                40295252,
                40295253,
                40295254,
                40295255,
                40295256,
                40295257,
                40295258,
                40295260,
                40295262,
                40295264,
                40295266,
                40295267,
                40295269
            ],
            "planet_id": 40295241
        }
    ],
    "position": {
        "x": -85728138376677970,
        "y": -9932263444726286,
        "z": -461322505602735500
    },
    "security_class": "G",
    "security_status": -0.08294060826301575,
    "star_id": 40295212,
    "stargates": [
        50010487,
        50010488,
        50010489
    ],
    "system_id": 30004671
}