{
    "constellation_id": 20000357,
    "name": "L4X-FH",
    "planets": [
        {
            "planet_id": 40154870
        },
        {
            "moons": [
                40154872
            ],
            "planet_id": 40154871
        },
        {
            "asteroid_belts": [
                40154874
            ],
            "moons": [
                40154875
            ],
            "planet_id": 40154873
        },
        {
            "asteroid_belts": [
                40154890
            ],
            "moons": [
                40154877,
                40154878,
                40154879,
                40154880,
                40154881,
                40154882,
                40154883,
                40154884,
                40154885,
                40154886,
                40154887,
                40154888,
                40154889
            ],
            "planet_id": 40154876
        },
        {
            "asteroid_belts": [
                40154892,
                40154893,
                40154900,
                40154909,
                40154916
            ],
            "moons": [
                40154894,
                40154895,
                40154896,
                40154897,
                40154898,
                40154899,
                40154901,
                40154902,
                40154903,
                40154904,
                40154905,
                40154906,
                40154907,
                40154908,
                40154910,
                40154911,
                40154912,
                40154913,
                40154914,
                40154915
            ],
            "planet_id": 40154891
        },
        {
            "asteroid_belts": [
                40154927
            ],
            "moons": [
                40154918,
                40154919,
                40154920,
                40154921,
                40154922,
                40154923,
                40154924,
                40154925,
                40154926,
                40154928
            ],
            "planet_id": 40154917
        },
        {
            "asteroid_belts": [
                40154930,
                40154931,
                40154932
            ],
            "planet_id": 40154929
        },
        {
            "asteroid_belts": [
                40154934,
                40154935,
                40154936
            ],
            "planet_id": 40154933
        }
    ],
    "position": {
        "x": -44928123103310056,
        "y": 47444091062084430,
        "z": 116061380190007460
    },
    "security_class": "H",
    "security_status": -0.07663089781999588,
    "star_id": 40154869,
    "stargates": [
        50005874,
        50005875
    ],
    "system_id": 30002435
}