{
    "constellation_id": 20000684,
    "name": "8Q-UYU",
    "planets": [
        {
            "moons": [
                40295902
            ],
            "planet_id": 40295901
        },
        {
            "asteroid_belts": [
                40295904
            ],
            "planet_id": 40295903
        },
        {
            "moons": [
                40295906
            ],
            "planet_id": 40295905
        },
        {
            "moons": [
                40295908
            ],
            "planet_id": 40295907
        },
        {
            "moons": [
                40295910,
                40295911
            ],
            "planet_id": 40295909
        },
        {
            "asteroid_belts": [
                40295913
            ],
            "moons": [
                40295914
            ],
            "planet_id": 40295912
        },
        {
            "asteroid_belts": [
                40295928
            ],
            "moons": [
                40295916,
                40295917,
                40295918,
                40295919,
                40295920,
                40295921,
                40295922,
                40295923,
                40295924,
                40295925,
                40295926,
                40295927,
                40295929,
                40295930
            ],
            "planet_id": 40295915
        },
        {
            "moons": [
                40295932,
                40295933
            ],
            "planet_id": 40295931
        },
        {
            "asteroid_belts": [
                40295936,
                40295952
            ],
            "moons": [
                40295935,
                40295937,
                40295938,
                40295939,
                40295940,
                40295941,
                40295942,
                40295943,
                40295944,
                40295945,
                40295946,
                40295947,
                40295948,
                40295949,
                40295950,
                40295951,
                40295953,
                40295954,
                40295955
            ],
            "planet_id": 40295934
        },
        {
            "moons": [
                40295957,
                40295958,
                40295959
            ],
            "planet_id": 40295956
        },
        {
            "asteroid_belts": [
                40295961
            ],
            "planet_id": 40295960
        }
    ],
    "position": {
        "x": -112200281098883360,
        "y": -51479779309203440,
        "z": -467382560775526900
    },
    "security_class": "G",
    "security_status": -0.016628524288535118,
    "star_id": 40295900,
    "stargates": [
        50011686,
        50011687,
        50011688,
        50011689
    ],
    "system_id": 30004681
}