{
    "constellation_id": 20000139,
    "name": "CI4M-T",
    "planets": [
        {
            "planet_id": 40060625
        },
        {
            "planet_id": 40060626
        },
        {
            "planet_id": 40060627
        },
        {
            "planet_id": 40060628
        },
        {
            "moons": [
                40060632,
                40060633
            ],
            "planet_id": 40060630
        },
        {
            "moons": [
                40060635,
                40060636,
                40060639,
                40060640,
                40060641,
                40060642,
                40060643,
                40060644,
                40060645,
                40060646,
                40060647,
                40060648,
                40060650,
                40060651,
                40060652
            ],
            "planet_id": 40060634
        },
        {
            "moons": [
                40060654,
                40060655,
                40060656,
                40060657,
                40060658,
                40060660
            ],
            "planet_id": 40060653
        },
        {
            "moons": [
                40060662,
                40060663
            ],
            "planet_id": 40060661
        },
        {
            "moons": [
                40060666,
                40060667,
                40060668
            ],
            "planet_id": 40060664
        }
    ],
    "position": {
        "x": 45823938378356280,
        "y": 36896288995187930,
        "z": -53817073845880290
    },
    "security_class": "I",
    "security_status": -0.030121617019176483,
    "star_id": 40060624,
    "stargates": [
        50002695,
        50002696
    ],
    "system_id": 30000951
}