{
    "constellation_id": 20000269,
    "name": "NQ-M6W",
    "planets": [
        {
            "asteroid_belts": [
                40116473
            ],
            "planet_id": 40116472
        },
        {
            "planet_id": 40116474
        },
        {
            "moons": [
                40116476
            ],
            "planet_id": 40116475
        },
        {
            "moons": [
                40116478
            ],
            "planet_id": 40116477
        },
        {
            "asteroid_belts": [
                40116481
            ],
            "moons": [
                40116480,
                40116482,
                40116483,
                40116484,
                40116485,
                40116486,
                40116487
            ],
            "planet_id": 40116479
        },
        {
            "moons": [
                40116489,
                40116490,
                40116491,
                40116492,
                40116493,
                40116494,
                40116495,
                40116496,
                40116497,
                40116498,
                40116499,
                40116500,
                40116501,
                40116502,
                40116503,
                40116504
            ],
            "planet_id": 40116488
        },
        {
            "asteroid_belts": [
                40116516
            ],
            "moons": [
                40116506,
                40116507,
                40116508,
                40116509,
                40116510,
                40116511,
                40116512,
                40116513,
                40116514,
                40116515
            ],
            "planet_id": 40116505
        },
        {
            "moons": [
                40116518,
                40116519,
                40116520,
                40116521,
                40116522,
                40116523,
                40116524,
                40116525,
                40116526,
                40116527,
                40116528,
                40116529,
                40116530,
                40116531,
                40116532,
                40116533,
                40116534,
                40116535,
                40116536,
                40116537,
                40116538
            ],
            "planet_id": 40116517
        },
        {
            "asteroid_belts": [
                40116540,
                40116542,
                40116544,
                40116547,
                40116557,
                40116560,
                40116563
            ],
            "moons": [
                40116543,
                40116545,
                40116546,
                40116548,
                40116549,
                40116550,
                40116551,
                40116552,
                40116553,
                40116554,
                40116555,
                40116556,
                40116558,
                40116559,
                40116561,
                40116562,
                40116564,
                40116565
            ],
            "planet_id": 40116539
        },
        {
            "asteroid_belts": [
                40116569,
                40116591,
                40116594,
                40116596,
                40116597,
                40116600,
                40116604,
                40116605
            ],
            "moons": [
                40116568,
                40116570,
                40116572,
                40116573,
                40116574,
                40116575,
                40116576,
                40116577,
                40116578,
                40116579,
                40116580,
                40116581,
                40116582,
                40116583,
                40116584,
                40116585,
                40116586,
                40116587,
                40116588,
                40116589,
                40116590,
                40116592,
                40116593,
                40116595,
                40116602
            ],
            "planet_id": 40116566
        },
        {
            "asteroid_belts": [
                40116607
            ],
            "moons": [
                40116608,
                40116609
            ],
            "planet_id": 40116606
        }
    ],
    "position": {
        "x": 301816602444390100,
        "y": -40458985154030940,
        "z": 69718502154078710
    },
    "security_class": "K4",
    "security_status": -0.5739356875419617,
    "star_id": 40116471,
    "stargates": [
        50013266,
        50013267,
        50013268
    ],
    "system_id": 30001822
}