{
    "constellation_id": 20000204,
    "name": "Korama",
    "planets": [
        {
            "moons": [
                40088671
            ],
            "planet_id": 40088670
        },
        {
            "moons": [
                40088673,
                40088674,
                40088675,
                40088676,
                40088677,
                40088678,
                40088679,
                40088680,
                40088681,
                40088682
            ],
            "planet_id": 40088672
        },
        {
            "asteroid_belts": [
                40088685,
                40088687,
                40088691
            ],
            "moons": [
                40088684,
                40088686,
                40088688,
                40088689,
                40088690,
                40088692,
                40088693,
                40088694,
                40088695,
                40088696,
                40088697,
                40088698,
                40088699,
                40088700,
                40088701
            ],
            "planet_id": 40088683
        },
        {
            "moons": [
                40088703,
                40088704,
                40088705,
                40088706,
                40088707,
                40088708,
                40088709,
                40088710,
                40088711,
                40088712,
                40088713,
                40088714,
                40088715,
                40088716,
                40088717,
                40088718,
                40088719
            ],
            "planet_id": 40088702
        },
        {
            "asteroid_belts": [
                40088722,
                40088741,
                40088744,
                40088746
            ],
            "moons": [
                40088721,
                40088723,
                40088724,
                40088725,
                40088726,
                40088727,
                40088728,
                40088729,
                40088730,
                40088731,
                40088732,
                40088733,
                40088734,
                40088735,
                40088736,
                40088737,
                40088738,
                40088739,
                40088740,
                40088742,
                40088743,
                40088745,
                40088747
            ],
            "planet_id": 40088720
        },
        {
            "asteroid_belts": [
                40088750,
                40088751,
                40088753,
                40088759,
                40088766,
                40088769,
                40088770,
                40088771,
                40088773,
                40088776,
                40088778,
                40088779,
                40088780,
                40088781,
                40088782
            ],
            "moons": [
                40088749,
                40088752,
                40088754,
                40088755,
                40088756,
                40088757,
                40088758,
                40088760,
                40088761,
                40088762,
                40088763,
                40088764,
                40088765,
                40088767,
                40088768,
                40088772,
                40088774,
                40088775,
                40088777,
                40088783
            ],
            "planet_id": 40088748
        },
        {
            "moons": [
                40088785,
                40088786
            ],
            "planet_id": 40088784
        }
    ],
    "position": {
        "x": -150178062411014240,
        "y": 104958330596204580,
        "z": 148377257895545000
    },
    "security_class": "B",
    "security_status": 0.770921528339386,
    "star_id": 40088669,
    "stargates": [
        50003448,
        50003449,
        50003450,
        50003451,
        50003452
    ],
    "stations": [
        60000766,
        60001576,
        60001582,
        60002068,
        60002071,
        60002074,
        60003733,
        60003967,
        60003970,
        60005140,
        60005146,
        60007549
    ],
    "system_id": 30001394
}