{
    "constellation_id": 20000632,
    "name": "B-GC1T",
    "planets": [
        {
            "planet_id": 40274102
        },
        {
            "planet_id": 40274103
        },
        {
            "moons": [
                40274105
            ],
            "planet_id": 40274104
        },
        {
            "asteroid_belts": [
                40274107
            ],
            "moons": [
                40274108
            ],
            "planet_id": 40274106
        },
        {
            "asteroid_belts": [
                40274110
            ],
            "moons": [
                40274111,
                40274112
            ],
            "planet_id": 40274109
        },
        {
            "moons": [
                40274114,
                40274115,
                40274116,
                40274117,
                40274118,
                40274119,
                40274120,
                40274121,
                40274122,
                40274123,
                40274124,
                40274125,
                40274126,
                40274127
            ],
            "planet_id": 40274113
        },
        {
            "asteroid_belts": [
                40274129,
                40274132
            ],
            "moons": [
                40274130,
                40274131
            ],
            "planet_id": 40274128
        },
        {
            "asteroid_belts": [
                40274134,
                40274142,
                40274150,
                40274152
            ],
            "moons": [
                40274135,
                40274136,
                40274137,
                40274138,
                40274139,
                40274140,
                40274141,
                40274143,
                40274144,
                40274145,
                40274146,
                40274147,
                40274148,
                40274149,
                40274151,
                40274153,
                40274154,
                40274155,
                40274156
            ],
            "planet_id": 40274133
        },
        {
            "asteroid_belts": [
                40274158
            ],
            "moons": [
                40274159,
                40274160,
                40274161,
                40274162
            ],
            "planet_id": 40274157
        }
    ],
    "position": {
        "x": -140881856026849200,
        "y": 47844130447986520,
        "z": 379698462367372300
    },
    "security_class": "H7",
    "security_status": -0.9032164216041565,
    "star_id": 40274101,
    "stargates": [
        50010630
    ],
    "system_id": 30004328
}