{
    "constellation_id": 20000333,
    "name": "Tastela",
    "planets": [
        {
            "planet_id": 40144833
        },
        {
            "moons": [
                40144835
            ],
            "planet_id": 40144834
        },
        {
            "planet_id": 40144836
        },
        {
            "asteroid_belts": [
                40144838
            ],
            "moons": [
                40144839
            ],
            "planet_id": 40144837
        },
        {
            "moons": [
                40144841
            ],
            "planet_id": 40144840
        },
        {
            "asteroid_belts": [
                40144846
            ],
            "moons": [
                40144843,
                40144844,
                40144845,
                40144847,
                40144848,
                40144849,
                40144850,
                40144851,
                40144852,
                40144853,
                40144854,
                40144855,
                40144856,
                40144857
            ],
            "planet_id": 40144842
        },
        {
            "moons": [
                40144859,
                40144860,
                40144861,
                40144862,
                40144863,
                40144864,
                40144865,
                40144866,
                40144867,
                40144868,
                40144869,
                40144870,
                40144871,
                40144872,
                40144873,
                40144874,
                40144875,
                40144876,
                40144877,
                40144878
            ],
            "planet_id": 40144858
        },
        {
            "asteroid_belts": [
                40144902
            ],
            "moons": [
                40144880,
                40144881,
                40144882,
                40144883,
                40144884,
                40144885,
                40144886,
                40144887,
                40144888,
                40144889,
                40144890,
                40144891,
                40144892,
                40144893,
                40144894,
                40144895,
                40144896,
                40144897,
                40144898,
                40144899,
                40144900,
                40144901
            ],
            "planet_id": 40144879
        },
        {
            "asteroid_belts": [
                40144904
            ],
            "moons": [
                40144905
            ],
            "planet_id": 40144903
        },
        {
            "moons": [
                40144907,
                40144908,
                40144909
            ],
            "planet_id": 40144906
        },
        {
            "asteroid_belts": [
                40144911
            ],
            "moons": [
                40144912,
                40144913
            ],
            "planet_id": 40144910
        }
    ],
    "position": {
        "x": -162657347844701950,
        "y": 41440830967122040,
        "z": -113622135370871220
    },
    "security_class": "B2",
    "security_status": 0.39112913608551025,
    "star_id": 40144832,
    "stargates": [
        50010820,
        50010821
    ],
    "system_id": 30002274
}