{
    "constellation_id": 20000382,
    "name": "01TG-J",
    "planets": [
        {
            "planet_id": 40166314
        },
        {
            "planet_id": 40166315
        },
        {
            "moons": [
                40166318
            ],
            "planet_id": 40166317
        },
        {
            "moons": [
                40166321
            ],
            "planet_id": 40166319
        },
        {
            "moons": [
                40166323,
                40166324
            ],
            "planet_id": 40166322
        },
        {
            "moons": [
                40166328,
                40166329,
                40166330,
                40166331
            ],
            "planet_id": 40166325
        },
        {
            "moons": [
                40166333,
                40166334,
                40166336,
                40166337,
                40166338,
                40166339,
                40166340,
                40166341,
                40166342,
                40166343,
                40166344,
                40166345,
                40166346,
                40166347,
                40166348,
                40166349,
                40166350,
                40166351,
                40166352
            ],
            "planet_id": 40166332
        },
        {
            "moons": [
                40166354,
                40166355,
                40166356,
                40166357,
                40166358
            ],
            "planet_id": 40166353
        },
        {
            "moons": [
                40166361
            ],
            "planet_id": 40166359
        }
    ],
    "position": {
        "x": -51170366458995970,
        "y": 18202280397755890,
        "z": -361422569793175000
    },
    "security_class": "F",
    "security_status": -0.15107464790344238,
    "star_id": 40166313,
    "stargates": [
        50008233,
        50008234
    ],
    "system_id": 30002609
}