{
    "constellation_id": 21000025,
    "name": "J232801",
    "planets": [
        {
            "planet_id": 40371727
        },
        {
            "planet_id": 40371728
        },
        {
            "moons": [
                40371730,
                40371731
            ],
            "planet_id": 40371729
        },
        {
            "planet_id": 40371732
        },
        {
            "moons": [
                40371734,
                40371735
            ],
            "planet_id": 40371733
        },
        {
            "moons": [
                40371737
            ],
            "planet_id": 40371736
        },
        {
            "moons": [
                40371739,
                40371740
            ],
            "planet_id": 40371738
        }
    ],
    "position": {
        "x": 7780873848356167000,
        "y": 60724236290113390,
        "z": -9351237276845906000
    },
    "security_status": -0.9900000095367432,
    "star_id": 40371726,
    "system_id": 31000403
}