{
    "constellation_id": 21000178,
    "name": "J153116",
    "planets": [
        {
            "planet_id": 40430934
        },
        {
            "planet_id": 40430935
        },
        {
            "moons": [
                40430937
            ],
            "planet_id": 40430936
        },
        {
            "moons": [
                40430939,
                40430940,
                40430941
            ],
            "planet_id": 40430938
        },
        {
            "moons": [
                40430943,
                40430944,
                40430945,
                40430946
            ],
            "planet_id": 40430942
        },
        {
            "planet_id": 40430947
        },
        {
            "moons": [
                40430949,
                40430950,
                40430951,
                40430952
            ],
            "planet_id": 40430948
        },
        {
            "moons": [
                40430954,
                40430955,
                40430956,
                40430957,
                40430958,
                40430959,
                40430960,
                40430961,
                40430962,
                40430963,
                40430964,
                40430965,
                40430966,
                40430967,
                40430968,
                40430969,
                40430970,
                40430971,
                40430972,
                40430973,
                40430974,
                40430975
            ],
            "planet_id": 40430953
        },
        {
            "moons": [
                40430977,
                40430978,
                40430979,
                40430980,
                40430981,
                40430982,
                40430983
            ],
            "planet_id": 40430976
        }
    ],
    "position": {
        "x": 7481267620746472000,
        "y": 40523791928503820,
        "z": -9537532122770145000
    },
    "security_status": -0.9900000095367432,
    "star_id": 40430933,
    "system_id": 31001542
}