{
    "constellation_id": 21000230,
    "name": "J152404",
    "planets": [
        {
            "planet_id": 40447687
        },
        {
            "moons": [
                40447689
            ],
            "planet_id": 40447688
        },
        {
            "planet_id": 40447690
        },
        {
            "moons": [
                40447692
            ],
            "planet_id": 40447691
        },
        {
            "moons": [
                40447694
            ],
            "planet_id": 40447693
        },
        {
            "moons": [
                40447696,
                40447697
            ],
            "planet_id": 40447695
        },
        {
            "moons": [
                40447699,
                40447700,
                40447701,
                40447702,
                40447703,
                40447704,
                40447705,
                40447706,
                40447707,
                40447708,
                40447709,
                40447710,
                40447711,
                40447712,
                40447713,
                40447714,
                40447715,
                40447716,
                40447717,
                40447718
            ],
            "planet_id": 40447698
        },
        {
            "moons": [
                40447720,
                40447721,
                40447722,
                40447723,
                40447724,
                40447725,
                40447726,
                40447727,
                40447728,
                40447729,
                40447730,
                40447731,
                40447732,
                40447733,
                40447734,
                40447735,
                40447736,
                40447737,
                40447738,
                40447739,
                40447740,
                40447741
            ],
            "planet_id": 40447719
        },
        {
            "moons": [
                40447743,
                40447744,
                40447745,
                40447746,
                40447747,
                40447748,
                40447749,
                40447750,
                40447751,
                40447752,
                40447753,
                40447754,
                40447755,
                40447756,
                40447757,
                40447758,
                40447759,
                40447760
            ],
            "planet_id": 40447742
        },
        {
            "moons": [
                40447762,
                40447763,
                40447764
            ],
            "planet_id": 40447761
        }
    ],
    "position": {
        "x": 8042271360378602000,
        "y": 29066901876665796,
        "z": -9689228410449600000
    },
    "security_status": -0.9900000095367432,
    "star_id": 40447686,
    "system_id": 31001872
}