{
    "constellation_id": 21000017,
    "name": "J105013",
    "planets": [
        {
            "moons": [
                40486484,
                40486485,
                40486486,
                40486487,
                40486488,
                40486489,
                40486490,
                40486491,
                40486492,
                40486493,
                40486494,
                40486495,
                40486496,
                40486497,
                40486498,
                40486499,
                40486500,
                40486501,
                40486502
            ],
            "planet_id": 40486483
        }
    ],
    "position": {
        "x": 7706696750930076000,
        "y": 46640076479386270,
        "z": -9358873031330064000
    },
    "security_status": -0.9900000095367432,
    "star_id": 40367272,
    "system_id": 31000316
}