{
    "constellation_id": 21000238,
    "name": "J131948",
    "planets": [
        {
            "planet_id": 40450782
        },
        {
            "planet_id": 40450783
        },
        {
            "moons": [
                40450785
            ],
            "planet_id": 40450784
        },
        {
            "moons": [
                40450787,
                40450788
            ],
            "planet_id": 40450786
        },
        {
            "planet_id": 40450789
        },
        {
            "moons": [
                40450791,
                40450792,
                40450793,
                40450794,
                40450795,
                40450796,
                40450797,
                40450798,
                40450799,
                40450800,
                40450801
            ],
            "planet_id": 40450790
        },
        {
            "moons": [
                40450803,
                40450804
            ],
            "planet_id": 40450802
        },
        {
            "moons": [
                40450806,
                40450807,
                40450808,
                40450809,
                40450810,
                40450811,
                40450812,
                40450813,
                40450814,
                40450815,
                40450816,
                40450817,
                40450818,
                40450819
            ],
            "planet_id": 40450805
        },
        {
            "moons": [
                40450821,
                40450822,
                40450823,
                40450824,
                40450825,
                40450826,
                40450827,
                40450828,
                40450829,
                40450830,
                40450831,
                40450832,
                40450833,
                40450834,
                40450835,
                40450836,
                40450837
            ],
            "planet_id": 40450820
        },
        {
            "moons": [
                40450839,
                40450840,
                40450841,
                40450842,
                40450843,
                40450844,
                40450845
            ],
            "planet_id": 40450838
        },
        {
            "moons": [
                40450847,
                40450848,
                40450849,
                40450850
            ],
            "planet_id": 40450846
        },
        {
            "planet_id": 40450851
        }
    ],
    "position": {
        "x": 7226073078278957000,
        "y": 43261431401415840,
        "z": -9346660362122449000
    },
    "security_status": -0.9900000095367432,
    "star_id": 40450781,
    "system_id": 31001931
}