{
    "constellation_id": 21000036,
    "name": "J134618",
    "planets": [
        {
            "planet_id": 40377817
        },
        {
            "moons": [
                40377819
            ],
            "planet_id": 40377818
        },
        {
            "moons": [
                40377821,
                40377822
            ],
            "planet_id": 40377820
        },
        {
            "planet_id": 40377823
        },
        {
            "moons": [
                40377825,
                40377826,
                40377827,
                40377828,
                40377829
            ],
            "planet_id": 40377824
        },
        {
            "moons": [
                40377831,
                40377832
            ],
            "planet_id": 40377830
        },
        {
            "moons": [
                40377834,
                40377835
            ],
            "planet_id": 40377833
        },
        {
            "moons": [
                40377837,
                40377838,
                40377839,
                40377840,
                40377841,
                40377842,
                40377843,
                40377844,
                40377845,
                40377846
            ],
            "planet_id": 40377836
        }
    ],
    "position": {
        "x": 7900039786599484000,
        "y": 52077635718483790,
        "z": -9540833109777537000
    },
    "security_status": -0.9900000095367432,
    "star_id": 40377816,
    "system_id": 31000516
}