{
    "constellation_id": 21000296,
    "name": "J101647",
    "planets": [
        {
            "moons": [
                40474841
            ],
            "planet_id": 40474840
        },
        {
            "planet_id": 40474842
        },
        {
            "moons": [
                40474845
            ],
            "planet_id": 40474844
        },
        {
            "planet_id": 40474846
        },
        {
            "moons": [
                40474849,
                40474850
            ],
            "planet_id": 40474848
        },
        {
            "moons": [
                40474853,
                40474854,
                40474855,
                40474856,
                40474857,
                40474858,
                40474859,
                40474860,
                40474861,
                40474862,
                40474863,
                40474864,
                40474866,
                40474867,
                40474868,
                40474869,
                40474870,
                40474871,
                40474872,
                40474873
            ],
            "planet_id": 40474852
        },
        {
            "moons": [
                40474876,
                40474877,
                40474878,
                40474879,
                40474880,
                40474881,
                40474882,
                40474883,
                40474884,
                40474885,
                40474886,
                40474887,
                40474888,
                40474889,
                40474890,
                40474891,
                40474892,
                40474893,
                40474896,
                40474897
            ],
            "planet_id": 40474875
        },
        {
            "moons": [
                40474901,
                40474902,
                40474903
            ],
            "planet_id": 40474899
        }
    ],
    "position": {
        "x": 7612539008940086000,
        "y": 35776625998743772,
        "z": -10017963022730900000
    },
    "security_status": -0.9900000095367432,
    "star_id": 40474839,
    "system_id": 31002361
}