{
    "constellation_id": 21000269,
    "name": "J213226",
    "planets": [
        {
            "planet_id": 40473015
        },
        {
            "planet_id": 40473016
        },
        {
            "moons": [
                40473019
            ],
            "planet_id": 40473018
        },
        {
            "moons": [
                40473021
            ],
            "planet_id": 40473020
        },
        {
            "moons": [
                40473023,
                40473025,
                40473026,
                40473027,
                40473028
            ],
            "planet_id": 40473022
        },
        {
            "moons": [
                40473031,
                40473032
            ],
            "planet_id": 40473029
        },
        {
            "moons": [
                40473034,
                40473036,
                40473037,
                40473038,
                40473039,
                40473040,
                40473041,
                40473042,
                40473043,
                40473044,
                40473045,
                40473046,
                40473047,
                40473048,
                40473049,
                40473050
            ],
            "planet_id": 40473033
        },
        {
            "moons": [
                40473052,
                40473057,
                40473061,
                40473062,
                40473063,
                40473064,
                40473065,
                40473066,
                40473067,
                40473068,
                40473069,
                40473070,
                40473071,
                40473072,
                40473073,
                40473074,
                40473075,
                40473076,
                40473077,
                40473078,
                40473079,
                40473080,
                40473081,
                40473083,
                40473084,
                40473086,
                40473087
            ],
            "planet_id": 40473051
        },
        {
            "moons": [
                40473090,
                40473091
            ],
            "planet_id": 40473088
        }
    ],
    "position": {
        "x": 8192132920278889000,
        "y": 5803082398601948,
        "z": -9302700118172744000
    },
    "security_status": -0.9900000095367432,
    "star_id": 40473014,
    "system_id": 31002163
}